apache_parser/__init__.py
apache_parser/parser.py
apache_parser/test_parser.py
apache_parser-0.0.2.dist-info/METADATA
apache_parser-0.0.2.dist-info/WHEEL
apache_parser-0.0.2.dist-info/top_level.txt
apache_parser-0.0.2.dist-info/RECORD
