Metadata-Version: 2.1
Name: apache-parser
Version: 0.0.2
Summary: UNKNOWN
Home-page: https://gitlab.com/lo4/apache_parser.git
Author: Phuong Huynh
Author-email: phuonghuynh.net@gmail.com
License: UNKNOWN
Platform: UNKNOWN
Classifier: Programming Language :: Python :: 3
Classifier: License :: OSI Approved :: MIT License
Classifier: Operating System :: OS Independent
